indifferent/__init__.py
indifferent/indifferent.py
indifferent-1.0.2.dist-info/LICENSE.md
indifferent-1.0.2.dist-info/METADATA
indifferent-1.0.2.dist-info/WHEEL
indifferent-1.0.2.dist-info/top_level.txt
indifferent-1.0.2.dist-info/RECORD
