Metadata-Version: 2.1
Name: indifferent
Version: 1.0.2
Summary: Compare two strings, calculate the match, and display the difference
Maintainer-email: Brian Warner <brian@bdwarner.com>
Project-URL: Homepage, https://brianwarner.github.io/indifferent/
Project-URL: Documentation, https://brianwarner.github.io/indifferent/
Project-URL: Repository, https://github.com/brianwarner/indifferent
Project-URL: Issues, https://github.com/brianwarner/indifferent/issues
Classifier: Development Status :: 5 - Production/Stable
Classifier: Intended Audience :: Developers
Classifier: Topic :: Text Processing :: Linguistic
Classifier: License :: OSI Approved :: MIT License
Requires-Python: >=3.10
License-File: LICENSE.md
Requires-Dist: rich
Requires-Dist: talkgooder
